Workbook
Name ______________________Tax1: #REF!
Name _____________________Tax1: #REF!
Name ____________________Tax1: #REF!
Name ___________________Tax1: #REF!
Name __________________Tax1: #REF!
Name _________________A99999: #REF!
Name _________________C99999: #REF!
Name _________________Tax1: #REF!
Name _________________Tax1: #REF!
Name ________________A99999: #REF!
Name ________________C99999: #REF!
Name ________________Tax1: #REF!
Name ________________Tax1: #REF!
Name _______________A99999: #REF!
Name _______________C99999: #REF!
Name _______________Tax1: #REF!
Name _______________Tax1: #REF!
Name ______________A99999: #REF!
Name ______________C99999: #REF!
Name ______________Tax1: #REF!
Name _____________A99999: #REF!
Name _____________C99999: #REF!
Name _____________Tax1: #REF!
Name ____________A99999: #REF!
Name ____________C99999: #REF!
Name ____________Tax1: #REF!
Name ___________A99999: #REF!
Name ___________C99999: #REF!
Name ___________Tax1: #REF!
Name __________A99999: #REF!
Name __________C99999: #REF!
Name __________Tax1: #REF!
Name _________A99999: #REF!
Name _________C99999: #REF!
Name _________Tax1: #REF!
Name ________A99999: #REF!
Name ________C99999: #REF!
Name ________Tax1: #REF!
Name _______A99999: #REF!
Name _______C99999: #REF!
Name _______Tax1: #REF!
Name ______A99999: #REF!
Name ______C99999: #REF!
Name ______Tax1: #REF!
Name _____A99999: #REF!
Name _____C99999: #REF!
Name _____Tax1: #REF!
Name ____A99999: #REF!
Name ____C99999: #REF!
Name ____Tax1: #REF!
Name ___A99999: #REF!
Name ___C99999: #REF!
Name ___Tax1: #REF!
Name __A99999: #REF!
Name __A99999: #REF!
Name __C99999: #REF!
Name __C99999: #REF!
Name __Tax1: #REF!
Name __xlnm.Print_Titles_3: ([2]L1!$A:$A,[2]L1!$1:$1)
Name _A99999: #REF!

Sheet Front
L1: D
A5: Client | B5: :- | H5: Preparer | K5: Date
A6: Financial Year | B6: :- | C6: As at 31/12/2024 | H6: Detail Reviewer | K6: Date
A7: FSA | B7: :- | C7: Property Plant and Equipment | H7: Gen. Reviewer | K7: Date
H8: Eng. Partner | K8: Date
A9: (all amounts in Qatari Riyals unless otherwise stated)
D11: Description | H11: As at 31/12/2023 | J11: As at 31/12/2022
D14: PPE | F14: PPE | H14: =Lead!F30 -> 0 | J14: =Lead!F31 -> 0
H15: =SUM(H14:H14) -> 0 | J15: =SUM(J14:J14) -> 0
A18: Work Done | E18: >> | F18: Checked the Opening Balance with Last Year Audited Accounts
E19: >> | F19: Check the Ledger Transactions.
E20: >> | F20: Check the during the year addition supporting documents with bank statement
E21: >> | F21: Check the Vehicle Isthimara
E22: >> | F22: Check the PPE register and Depreciation calculation
E23: >> | F23: Agreed with Closing Balance with Ledger
A26: Audit Objectives | E26: >> | F26: To ensure the valuation, existence, completeness, Rights and Obligation of above balance.
A30: Audit Notes | E30: >> | F30: Note
A35: Audit Findings | E35: >>
A42: Conclusions | E42: >> | F42: Accounts are fairly stated.

Sheet Lead
A1: Client: | F1: D1
A2: Financial Year: As at 31/12/2024
A3: FSA: PPE
B5: Furniture and fittings | D5: Motor Vehicles | F5: Total
A6: PROPERTY AND EQUIPMENT
A7: Cost
A8: Balance as at 01 January 2023 | B8: 0 | D8: 0 | F8: =SUM(B8:D8) -> 0
A9: Additions | B9: 0 | D9: 0 | F9: 0
A10: Disposals | B10: 0 | D10: 0 | F10: =SUM(B10:D10) -> 0
A11: Balance as at 31 December 2023 | B11: =SUM(B8:B10) -> 0 | D11: =SUM(D8:D10) -> 0 | F11: =SUM(F8:F10) -> 0
A13: Balance as at 01 January 2024 | B13: =B11 -> 0 | D13: =D11 -> 0 | F13: =SUM(B13:D13) -> 0
A14: Additions | B14: 0 | D14: 0 | F14: 0
A15: Disposals | B15: 0 | D15: 0 | F15: =SUM(B15:D15) -> 0
A16: Balance as at 31 December 2024 | B16: =SUM(B13:B15) -> 0 | D16: =SUM(D13:D15) -> 0 | F16: =SUM(F13:F15) -> 0
A18: Accumulated Depreciation
A19: Balance as at 01 January 2023 | B19: 0 | D19: 0 | F19: =SUM(B19:D19) -> 0
A20: Charge for the year | B20: 0 | D20: 0 | F20: =SUM(B20:D20) -> 0
A21: Disposal during the year | B21: 0 | D21: 0 | F21: 0
A22: =A11 -> Balance as at 31 December 2023 | B22: =SUM(B19:B21) -> 0 | D22: =SUM(D19:D21) -> 0 | F22: =SUM(F19:F21) -> 0
A24: Balance as at 01 January 2024 | B24: =B22 -> 0 | D24: =D22 -> 0 | F24: =SUM(B24:D24) -> 0
A25: Charge for the year | B25: 0 | D25: 0 | F25: =SUM(B25:D25) -> 0
A26: Disposal during the year | B26: 0 | D26: 0 | F26: =SUM(B26:D26) -> 0
A27: Balance as at 31 December 2024 | B27: =SUM(B24:B26) -> 0 | D27: =SUM(D24:D26) -> 0 | F27: =SUM(F24:F26) -> 0
A29: Carrying amounts
A30: Balance as at 31 December 2024 | B30: =B16-B27 -> 0 | D30: =D16-D27 -> 0 | F30: =F16-F27 -> 0
A31: Balance as at 31 December 2023 | B31: =B11-B22 -> 0 | D31: =D11-D22 -> 0 | F31: =F11-F22 -> 0

Sheet Depreciation
A1: Client: Gulf Furniture and Services W.L.L | E1: D3
A2: Financial Year: As at 31/12/2021
A3: FSA: PPE
A5: Depreciation
B7: Motor vehicles | C7: Furniture and fixtures | D7: Total
A9: Book Value as at 30/12/2020 | B9: 13133 | C9: 57139 | D9: =SUM(B9:C9) -> 70272
A10: (*) Tax rates | B10: 0.15 | C10: 0.2
A11: Depreciation (1) | B11: =B9*B10 -> 1969.95 | C11: =C9*C10 -> 11427.8 | D11: =SUM(B11:C11) -> 13397.75
A13: Additions
A14: MV | B14: 0 | C14: 152640 | D14: 0
A15: MV | C15: 20000
A16: MV | C16: 97000
A17: MV | C17: 5798
B19: 0 | C19: 0.2 | D19: 0
A20: Dep on Addition (2) | B20: =B14*B19 -> 0 | C20: =(C14*C19*11/12)+(C15*C19*9/12)+(C16*C19*1/12) -> 32600.667
A21: Total Depreciation expense (1+2) | B21: =B11+B20 -> 1969.95 | C21: =C11+C20 -> 44028.467 | D21: =SUM(B21:C21) -> 45998.417

Sheet Dep computation
A1: Assets Register
D2: 218834
A3: MOTOR VECHILES
A4: CAR NO | B4: CENTRA 626403 | C4: CENTRA 647017 | D4: CENTRA 218384 | E4: CENTRA 600711 | F4: BMW 511214 | G4: MERC 622505 | H4: CENTRA 727908 | I4: PICKUP 133376
A5: DOP | B5: 42781 | C5: 42844 | D5: 42864 | E5: 43367 | F5: 43379 | G5: 44211 | H5: 44273 | I5: 44528
A6: COST | B6: 22000 | C6: 29700 | D6: =27500+4700 -> 32200 | E6: 24000 | F6: 35000 | G6: 152740 | H6: 20500 | I6: 102798 | J6: =SUM(B6:I6) -> 418938
A9: DEPN TILL DEC 2021 | B9: 0 | C9: 17335 | D9: 18234 | E9: 11712 | F9: 17080 | G9: 27984 | H9: 3000 | I9: 1713 | J9: =SUM(B9:I9) -> 97058
A10: WDV AS ON 31 DEC 2021 | B10: 0 | C10: =C6-C9 -> 12365 | D10: =D6-D9 -> 13966 | E10: =E6-E9 -> 12288 | F10: =F6-F9 -> 17920 | G10: =G6-G9 -> 124756 | H10: =H6-H9 -> 17500 | I10: =I6-I9 -> 101085 | J10: =SUM(B10:I10) -> 299880
A11: DEP FOR YEAR 2022 (wdv*20%) | C11: =ROUND(C10*0.2,0) -> 2473 | D11: SOLD JAN22 | E11: =ROUND(E10*0.2,0) -> 2458 | F11: =ROUND(F10*0.2,0) -> 3584 | G11: =ROUND(G10*0.2,0) -> 24951 | H11: =ROUND(H10*0.2,0) -> 3500 | I11: =ROUND(I10*0.2,0) -> 20217 | J11: =SUM(B11:I11) -> 57183
A12: WDV AS ON 31-12-2022 | C12: =C10-C11 -> 9892 | D12: 0 | E12: =E10-E11 -> 9830 | F12: =F10-F11 -> 14336 | G12: =G10-G11 -> 99805 | H12: =H10-H11 -> 14000 | I12: =I10-I11 -> 80868 | J12: =SUM(B12:I12) -> 228731

Sheet Addition and Disposal
A1: =Lead!A1 -> Client: | F1: D2
A2: =Lead!A2 -> Financial Year: As at 31/12/2024
A3: =Lead!A3 -> FSA: PPE
A5: Additions Breakup
A7: Purchase Date | B7: Description | C7: Amount (QR) | D7: PV No. | E7: Supporting | F7: BS Date
C8: 0 | D8: - | E8: Yes

Sheet Depreciation Cal
A1: =Lead!A1 -> Client: | I1: D3
A2: =Lead!A2 -> Financial Year: As at 31/12/2024
A3: =Lead!A3 -> FSA: PPE
A5: Depreciation
B7: Purchase Date | C7: Cost | D7: Acc.Deptn as at 31/12/2022 | E7: W.D.V as at 31/12/2022 | F7: Dep. Rate | G7: During the Year Deptn | H7: Acc.Deptn as at 31/12/2023 | I7: W.D.V as at 31/12/2023
A8: Vehicles
C9: 0 | E9: =C9-D9 -> 0 | F9: 0.2 | G9: =ROUND((E9*F9),0) -> 0 | H9: =G9+D9 -> 0 | I9: =C9-H9 -> 0
C10: 0 | E10: =C10-D10 -> 0 | F10: 0.2 | G10: =ROUND((E10*F10),0) -> 0 | H10: =G10+D10 -> 0 | I10: =C10-H10 -> 0
C11: 0 | E11: =C11-D11 -> 0 | F11: 0.2 | G11: =ROUND((E11*F11),0) -> 0 | H11: =G11+D11 -> 0 | I11: =C11-H11 -> 0
C12: 0 | E12: =C12-D12 -> 0 | F12: 0.2 | G12: =ROUND((E12*F12),0) -> 0 | H12: =G12+D12 -> 0 | I12: =C12-H12 -> 0
C13: 0 | E13: =C13-D13 -> 0 | F13: 0.2 | G13: =ROUND((E13*F13),0) -> 0 | H13: =G13+D13 -> 0 | I13: =C13-H13 -> 0
C14: 0 | E14: =C14-D14 -> 0 | F14: 0.2 | G14: =ROUND((E14*F14),0) -> 0 | H14: =G14+D14 -> 0 | I14: =C14-H14 -> 0
C15: 0 | E15: =C15-D15 -> 0 | F15: 0.2 | G15: =E15*F15*2/12 -> 0 | H15: =G15+D15 -> 0 | I15: =C15-H15 -> 0
C16: =SUM(C9:C15) -> 0 | D16: =SUM(D9:D15) -> 0 | E16: =SUM(E9:E15) -> 0 | G16: =SUM(G9:G15) -> 0 | H16: =SUM(H9:H15) -> 0 | I16: =SUM(I9:I15) -> 0
A18: Furniture and Fittings
C20: =SUM(C19:C19) -> 0 | D20: =SUM(D19:D19) -> 0 | G20: =SUM(G19:G19) -> 0 | H20: =SUM(H19:H19) -> 0 | I20: =SUM(I19:I19) -> 0
C22: =C16+C20 -> 0 | G22: =G16+G20 -> 0 | H22: =H16+H20 -> 0 | I22: =I16+I20 -> 0
